{
    "Ar36": {
        "error": 0.0004236532606477106,
        "error_type": "SEM",
        "filter_outliers_dict": {
            "filter_outliers": true,
            "iterations": 1,
            "std_devs": 2
        },
        "fit": "Parabolic",
        "value": 0.07348580494263379
    },
    "Ar37": {
        "error": 0.010866172854958283,
        "error_type": "SEM",
        "filter_outliers_dict": {
            "filter_outliers": true,
            "iterations": 1,
            "std_devs": 2
        },
        "fit": "Linear",
        "value": -0.9654589793849662
    },
    "Ar38": {
        "error": 0.008983973679105379,
        "error_type": "SEM",
        "filter_outliers_dict": {
            "filter_outliers": true,
            "iterations": 1,
            "std_devs": 2
        },
        "fit": "Linear",
        "value": 0.1573127141708478
    },
    "Ar39": {
        "error": 0.014174382207177429,
        "error_type": "SEM",
        "filter_outliers_dict": {
            "filter_outliers": true,
            "iterations": 1,
            "std_devs": 2
        },
        "fit": "Parabolic",
        "value": -0.08587375929226465
    },
    "Ar40": {
        "error": 0.014002290622488135,
        "error_type": "SEM",
        "filter_outliers_dict": {
            "filter_outliers": true,
            "iterations": 1,
            "std_devs": 2
        },
        "fit": "Parabolic",
        "value": 0.7244544203685521
    },
    "PM41": {
        "error": 0.024785428054664844,
        "error_type": null,
        "filter_outliers_dict": {
            "filter_outliers": false,
            "iterations": 1,
            "std_devs": 2
        },
        "fit": "linear",
        "value": 1.164765988385529
    }
}